{
  "pe": "lisa",
  "week": "June 15 – June 22, 2026",
  "refreshedAt": "2026-06-22T16:00:00Z",
  "updates": [
    {
      "heading": "VMA Interviewers Needed — L1 Jr. Onboarding Associate Sprint",
      "bullets": [
        "Grace flagged 3–5 candidates likely needing VMAs between June 18–22",
        "Existing VMA pool exhausted on short notice — Grace asked team for on-call coverage"
      ]
    },
    {
      "heading": "Comp Range Access Check-In",
      "bullets": [
        "Lisa checked in June 18 on whether team can access new Workday comp ranges",
        "Anyone with difficulty should flag in the #gtm_invite_pod thread"
      ]
    },
    {
      "heading": "Denver Hub Guidance Resolved for Non-MSA Employees",
      "bullets": [
        "Grace surfaced guidance for Denver-based folks outside the MSA",
        "Lisa confirmed: use Grace’s guidance as the plan going forward",
        "Relevant for JT, Will, and Gina for Denver-based hiring logistics"
      ]
    },
    {
      "heading": "Talent Insights Slide Deck Templates Shared",
      "bullets": [
        "Grace shared slide deck templates from the team sync for talent insights presentations to HMs",
        "Once the Greenhouse MCP is available, Grace will share a skill for auto-generating these slides",
        "For now, data is being entered manually"
      ]
    },
    {
      "heading": "PeopleOS — GTM Pod Check-In",
      "bullets": [
        "Lisa asked the team to log in to PeopleOS and report back on what they see (June 16)",
        "Loom walkthrough of new features shared: https://www.loom.com/share/aabf4bd1aec243a39d47abba4df6c82b"
      ]
    },
    {
      "heading": "Hiring Manager Survey — Active Push",
      "bullets": [
        "Lisa reminded team to send the HM Survey at the close of every req with a successful hire",
        "Responses are coming in; link in the HM Survey GSheet"
      ]
    }
  ]
}